gradman/__init__.py
gradman/ctg.py
gradman/nn.py
gradman/ops.py
gradman/optim.py
gradman/tensor.py
gradman-0.0.1b9.dist-info/LICENSE
gradman-0.0.1b9.dist-info/WHEEL
gradman-0.0.1b9.dist-info/METADATA
gradman-0.0.1b9.dist-info/RECORD
