Metadata-Version: 2.1
Name: gradman
Version: 0.0.1b9
Summary: Baby Deep Learning Library
License: MIT
Author: tanmoyio
Author-email: tanmoyf2@gmail.com
Requires-Python: >=3.6,<4.0
Classifier: License :: OSI Approved :: MIT License
Classifier: Programming Language :: Python :: 3
Classifier: Programming Language :: Python :: 3.10
Classifier: Programming Language :: Python :: 3.6
Classifier: Programming Language :: Python :: 3.7
Classifier: Programming Language :: Python :: 3.8
Classifier: Programming Language :: Python :: 3.9
Requires-Dist: numpy (>=1.21.5,<2.0.0)
